shcheck/__init__.py
shcheck/shcheck.py
shcheck-1.6.6.data/scripts/shcheck.py
shcheck-1.6.6.dist-info/LICENSE.txt
shcheck-1.6.6.dist-info/METADATA
shcheck-1.6.6.dist-info/WHEEL
shcheck-1.6.6.dist-info/top_level.txt
shcheck-1.6.6.dist-info/RECORD
