Metadata-Version: 2.1
Name: shcheck
Version: 1.6.6
Summary: A basic tool to check security headers of a website
Home-page: https://github.com/santoru/shcheck
Author: santoru
Author-email: santoru@pm.me
Requires-Python: >=3
License-File: LICENSE.txt
